halo/__init__.py
halo/client.py
halo_sdk-0.1.1.dist-info/METADATA
halo_sdk-0.1.1.dist-info/WHEEL
halo_sdk-0.1.1.dist-info/top_level.txt
halo_sdk-0.1.1.dist-info/RECORD
