Metadata-Version: 2.1
Name: halo-sdk
Version: 0.1.1
Summary: Python SDK for Halo API with built-in x402 auto-payment
Home-page: UNKNOWN
Author: Halo Team
License: UNKNOWN
Keywords: halo,x402,payment,ai,llm,gemini
Platform: UNKNOWN
Requires-Python: >=3.7
Requires-Dist: requests>=2.25.0
Requires-Dist: web3>=6.0.0
Requires-Dist: google-generativeai>=0.3.0
Requires-Dist: eth-account>=0.5.9
